core/__init__.py
core/xmlobject.py
pydrawio/__init__.py
pydrawio/mxfile.py
pydrawio/mxgraphmodel.py
pydrawio/mxlibrary.py
pydrawio-1.1.0.dist-info/LICENSE.md
pydrawio-1.1.0.dist-info/METADATA
pydrawio-1.1.0.dist-info/WHEEL
pydrawio-1.1.0.dist-info/top_level.txt
pydrawio-1.1.0.dist-info/RECORD
