Metadata-Version: 2.1
Name: pydrawio
Version: 1.1.0
Summary: pydrawio: manage draw.io file
Home-page: https://github.com/capybara-alt/pydrawio
Download-URL: https://github.com/capybara-alt/pydrawio
Author: Naoto Kageyama
Author-email: rencker3@gmail.com
Maintainer: Naoto Kageyama
Maintainer-email: rencker3@gmail.com
License: MIT
Classifier: License :: OSI Approved :: MIT License
Classifier: Programming Language :: Python :: 3.7
Classifier: Programming Language :: Python :: 3.8
Classifier: Programming Language :: Python :: 3.9
Requires-Python: >=3.7
License-File: LICENSE.md
